AUTHORS
BUGS.md
CHANGES.rst
LICENSE
MANIFEST.in
README.rst
TODO.md
setup.py
jhunt/__init__.py
jhunt.egg-info/PKG-INFO
jhunt.egg-info/SOURCES.txt
jhunt.egg-info/dependency_links.txt
jhunt.egg-info/entry_points.txt
jhunt.egg-info/requires.txt
jhunt.egg-info/top_level.txt
jhunt/data/__init__.py
jhunt/data/adverts.py
jhunt/data/websites.py
jhunt/io/__init__.py
jhunt/io/adverts.py
jhunt/io/lock.py
jhunt/io/websites.py
jhunt/qt/__init__.py
jhunt/qt/main.py
jhunt/qt/delegates/__init__.py
jhunt/qt/delegates/adverts.py
jhunt/qt/delegates/websites.py
jhunt/qt/models/__init__.py
jhunt/qt/models/adverts.py
jhunt/qt/models/websites.py
jhunt/qt/widgets/__init__.py
jhunt/qt/widgets/mainwindow.py
jhunt/qt/widgets/plot.py
jhunt/qt/widgets/tabs/__init__.py
jhunt/qt/widgets/tabs/adverts.py
jhunt/qt/widgets/tabs/stats.py
jhunt/qt/widgets/tabs/websites.py