Metadata-Version: 1.2
Name: jhunt
Version: 2.0
Summary: A tool to manage job adverts for job seekers
Home-page: https://github.com/jeremiedecock/jhunt
Author: Jeremie DECOCK
Author-email: jd.jdhp@gmail.com
Maintainer: Jeremie DECOCK
Maintainer-email: jd.jdhp@gmail.com
License: UNKNOWN
Download-URL: https://github.com/jeremiedecock/jhunt
Keywords: job hunter
Platform: UNKNOWN
Classifier: Development Status :: 4 - Beta
Classifier: License :: OSI Approved :: MIT License
Classifier: Natural Language :: English
Classifier: Operating System :: OS Independent
Classifier: Programming Language :: Python :: 3
Classifier: Topic :: Documentation
